[
    {
        "id":"1",
        "title":"Some title 1",
        "undertitle":"Some undtitle 1",
        "text":"Some text text text text text"
    },
    {
        "id":"2",
        "title":"Some title 2",
        "undertitle":"Some undtitle 2",
        "text":"Some text text text text text"
    },
    {
        "id":"3",
        "title":"Some title 3",
        "undertitle":"Some undtitle 3",
        "text":"Some text text text text text"
    },
    {
        "id":"4",
        "title":"Some title 4",
        "undertitle":"Some undtitle 4",
        "text":"Some text text text text text"
    },
    {
        "id":"5",
        "title":"Some title 5",
        "undertitle":"Some undtitle 5",
        "text":"Some text text text text text"
    },
    {
        "id":"6",
        "title":"Some title 6",
        "undertitle":"Some undtitle 6",
        "text":"Some text text text text text"
    },
    {
        "id":"7",
        "title":"Some title 7",
        "undertitle":"Some undtitle 7",
        "text":"Some text text text text text"
    },
    {
        "id":"8",
        "title":"Some title 8",
        "undertitle":"Some undtitle 8",
        "text":"Some text text text text text"
    },
    {
        "id":"9",
        "title":"Some title 9",
        "undertitle":"Some undtitle 9",
        "text":"Some text text text text text"
    },
    {
        "id":"10",
        "title":"Some title 10",
        "undertitle":"Some undtitle 10",
        "text":"Some text text text text text"
    }
    
]